healthcards/__init__.py
healthcards/cvx.py
healthcards/parser.py
healthcards-0.1.6.dist-info/LICENSE
healthcards-0.1.6.dist-info/METADATA
healthcards-0.1.6.dist-info/WHEEL
healthcards-0.1.6.dist-info/top_level.txt
healthcards-0.1.6.dist-info/RECORD
