Metadata-Version: 2.1
Name: healthcards
Version: 0.1.6
Summary: Python parser for https://spec.smarthealth.cards
Home-page: https://github.com/rechner/py-health-cards
Author: Rechner Fox
License: MIT
Classifier: Programming Language :: Python :: 3
Classifier: License :: OSI Approved :: MIT License
Classifier: Operating System :: OS Independent
Requires-Python: >=3.7
License-File: LICENSE
Requires-Dist: jwcrypto
